CHANGELOG.md
LICENSE
MANIFEST.in
README.md
setup.py
manuale/__init__.py
manuale/account.py
manuale/acme.py
manuale/authorize.py
manuale/cli.py
manuale/crypto.py
manuale/errors.py
manuale/helpers.py
manuale/info.py
manuale/issue.py
manuale/register.py
manuale/revoke.py
manuale.egg-info/PKG-INFO
manuale.egg-info/SOURCES.txt
manuale.egg-info/dependency_links.txt
manuale.egg-info/entry_points.txt
manuale.egg-info/requires.txt
manuale.egg-info/top_level.txt