Metadata-Version: 1.1
Name: manuale
Version: 1.0.1
Summary: A fully manual Let's Encrypt/ACME client
Home-page: https://github.com/veeti/manuale
Author: Veeti Paananen
Author-email: veeti.paananen@rojekti.fi
License: MIT
Platform: UNKNOWN
Classifier: Development Status :: 4 - Beta
Classifier: License :: OSI Approved :: MIT License
Classifier: Environment :: Console
Classifier: Intended Audience :: Developers
Classifier: Intended Audience :: System Administrators
Classifier: Programming Language :: Python :: 3
Classifier: Programming Language :: Python :: 3.3
Classifier: Programming Language :: Python :: 3.4
Classifier: Programming Language :: Python :: 3.5
Classifier: Programming Language :: Python :: 3 :: Only
